setch/__init__.py
setch/__main__.py
setch/core.py
setch/sys/__init__.py
setch/sys/check.py
setch/sys/info.py
setch_py-1.0.8.dist-info/METADATA
setch_py-1.0.8.dist-info/WHEEL
setch_py-1.0.8.dist-info/entry_points.txt
setch_py-1.0.8.dist-info/licenses/LICENSE
setch_py-1.0.8.dist-info/RECORD
