Metadata-Version: 2.4
Name: setch-py
Version: 1.0.8
Summary: Utility for retrieving system information on Linux
Project-URL: Source, https://github.com/mentiferous/setch.git
Author: mentiferous
License-Expression: GPL-3.0-or-later
License-File: LICENSE
Keywords: linux,setch,setch-py,utility
Classifier: Development Status :: 5 - Production/Stable
Classifier: Environment :: Console
Classifier: Intended Audience :: End Users/Desktop
Classifier: License :: OSI Approved :: GNU General Public License v3 or later (GPLv3+)
Classifier: Natural Language :: English
Classifier: Operating System :: POSIX :: Linux
Classifier: Programming Language :: Python
Classifier: Programming Language :: Python :: 3
Classifier: Programming Language :: Python :: 3 :: Only
Classifier: Programming Language :: Python :: 3.10
Classifier: Programming Language :: Python :: 3.11
Classifier: Programming Language :: Python :: 3.12
Classifier: Programming Language :: Python :: 3.13
Classifier: Topic :: Utilities
Requires-Python: >=3.10
